local_resources/__init__.py
local_resources/local_resources.py
local_resources-1.0.2.dist-info/LICENSE
local_resources-1.0.2.dist-info/METADATA
local_resources-1.0.2.dist-info/WHEEL
local_resources-1.0.2.dist-info/top_level.txt
local_resources-1.0.2.dist-info/RECORD
