Metadata-Version: 2.1
Name: local_resources
Version: 1.0.2
Summary: Ability to fetch resources similar to Java Class.getResource()
Home-page: https://github.com/Abstract-Horizon/local_resources
Author: Daniel Sendula
License: UNKNOWN
Platform: UNKNOWN
Classifier: Programming Language :: Python :: 3
Classifier: License :: OSI Approved :: Apache Software License
Classifier: Operating System :: OS Independent
Requires-Python: >=3.6
License-File: LICENSE
